dump_things_service/__about__.py
dump_things_service/__init__.py
dump_things_service/api_key.py
dump_things_service/config.py
dump_things_service/conftest.py
dump_things_service/converter.py
dump_things_service/curated.py
dump_things_service/dynamic_endpoints.py
dump_things_service/exceptions.py
dump_things_service/incoming.py
dump_things_service/lazy_list.py
dump_things_service/main.py
dump_things_service/model.py
dump_things_service/resolve_curie.py
dump_things_service/token.py
dump_things_service/utils.py
dump_things_service/auth/__init__.py
dump_things_service/auth/config.py
dump_things_service/auth/forgejo.py
dump_things_service/backends/__init__.py
dump_things_service/backends/mongo.py
dump_things_service/backends/record_dir.py
dump_things_service/backends/record_dir_index.py
dump_things_service/backends/schema_type_layer.py
dump_things_service/backends/sqlite.py
dump_things_service/backends/tests/__init__.py
dump_things_service/backends/tests/test_record_dir.py
dump_things_service/backends/tests/test_record_dir_index.py
dump_things_service/commands/__init__.py
dump_things_service/commands/check_pids.py
dump_things_service/commands/copy_store.py
dump_things_service/commands/create_merged_schema.py
dump_things_service/commands/rebuild_index.py
dump_things_service/export/__init__.py
dump_things_service/export/json.py
dump_things_service/export/tree.py
dump_things_service/patches/__init__.py
dump_things_service/patches/compile.py
dump_things_service/patches/enabled.py
dump_things_service/patches/enumerations.py
dump_things_service/patches/ifabsent_processing.py
dump_things_service/patches/pythongen_gen_references.py
dump_things_service/patches/rdflib_loader.py
dump_things_service/patches/yamlutils.py
dump_things_service/schemas/cfp1.ttl
dump_things_service/schemas/grants.yaml
dump_things_service/schemas/json2nt.py
dump_things_service/schemas/ttl2nt.py
dump_things_service/schemas/yaml2nt.py
dump_things_service/schemas/example/CallForApplication-1.yaml
dump_things_service-5.3.6.dist-info/METADATA
dump_things_service-5.3.6.dist-info/WHEEL
dump_things_service-5.3.6.dist-info/entry_points.txt
dump_things_service-5.3.6.dist-info/RECORD
