Metadata-Version: 2.4
Name: dump-things-service
Version: 5.3.6
Summary: A simple service to store and retrieve schema-conform data records
Project-URL: Documentation, https://github.com/christian-monch/dump-things-server
Project-URL: Issues, https://github.com/christian-monch/dump-things-server/issues
Project-URL: Source, https://github.com/christian-monch/dump-things-server
Author-email: Christian Mönch <christian.moench@web.de>
License-Expression: MIT
Classifier: Development Status :: 4 - Beta
Classifier: Programming Language :: Python
Classifier: Programming Language :: Python :: 3.8
Classifier: Programming Language :: Python :: 3.9
Classifier: Programming Language :: Python :: 3.10
Classifier: Programming Language :: Python :: 3.11
Classifier: Programming Language :: Python :: 3.12
Classifier: Programming Language :: Python :: Implementation :: CPython
Classifier: Programming Language :: Python :: Implementation :: PyPy
Requires-Python: >=3.8
Requires-Dist: aiohttp
Requires-Dist: click
Requires-Dist: fastapi-pagination
Requires-Dist: fastapi[standard]
Requires-Dist: fsspec
Requires-Dist: linkml
Requires-Dist: pydantic
Requires-Dist: pyyaml
Requires-Dist: rdflib
Requires-Dist: requests
Requires-Dist: sqlalchemy
Requires-Dist: uvicorn
